mac_internet_sharing/__init__.py
mac_internet_sharing/__main__.py
mac_internet_sharing/_version.py
mac_internet_sharing/dhcpd_leases.py
mac_internet_sharing/exceptions.py
mac_internet_sharing/mac_internet_sharing.py
mac_internet_sharing/native_bridge.py
mac_internet_sharing/network_preference.py
mac_internet_sharing-0.1.2.dist-info/METADATA
mac_internet_sharing-0.1.2.dist-info/WHEEL
mac_internet_sharing-0.1.2.dist-info/entry_points.txt
mac_internet_sharing-0.1.2.dist-info/top_level.txt
mac_internet_sharing-0.1.2.dist-info/RECORD
