Metadata-Version: 2.4
Name: mac-internet-sharing
Version: 0.1.2
Summary: Mac Internet Sharing Helper
Author-email: netanelc305 <netanelc305@protonmail.com>
Maintainer-email: netanelc305 <netanelc305@protonmail.com>
License: GNU GENERAL PUBLIC LICENSE Version 3, 29 June 2007
Project-URL: Homepage, https://github.com/netanelc305/mac_internet_sharing
Project-URL: Bug Reports, https://github.com/netanelc305/mac_internet_sharing/issues
Keywords: macos,osx,internet sharing,automation,cli,ioservice
Classifier: Development Status :: 5 - Production/Stable
Classifier: License :: OSI Approved :: GNU General Public License v3 or later (GPLv3+)
Classifier: Operating System :: MacOS
Classifier: Programming Language :: Python :: 3
Classifier: Programming Language :: Python :: 3.9
Classifier: Programming Language :: Python :: 3.10
Classifier: Programming Language :: Python :: 3.11
Classifier: Programming Language :: Python :: 3.12
Classifier: Programming Language :: Python :: 3.13
Classifier: Programming Language :: Python :: 3 :: Only
Requires-Python: >=3.9
Requires-Dist: ioregistry
Requires-Dist: click
Requires-Dist: psutil
Requires-Dist: inquirer3
Requires-Dist: plumbum
Requires-Dist: coloredlogs
